aves/__init__.py
aves/explorer.py
aves/gui.py
aves/io.py
aves/realtime.py
aves-3.0.1.dist-info/LICENSE
aves-3.0.1.dist-info/METADATA
aves-3.0.1.dist-info/WHEEL
aves-3.0.1.dist-info/top_level.txt
aves-3.0.1.dist-info/RECORD
