Metadata-Version: 2.1
Name: aves
Version: 3.0.1
Summary: Acquisition, Visualization and Exploration Software
Home-page: https://github.com/zeehio/aves
Author: Sergio Oller Moreno
Author-email: sergioller@gmail.com
License: UNKNOWN
Platform: UNKNOWN
Classifier: Programming Language :: Python :: 3
Classifier: License :: OSI Approved :: MIT License
Classifier: Operating System :: OS Independent
Requires-Dist: pyserial
Requires-Dist: matplotlib
